rafm/__init__.py
rafm/__main__.py
rafm/common.py
rafm/plddt.py
rafm/py.typed
rafm-1.1.4.dist-info/entry_points.txt
rafm-1.1.4.dist-info/LICENSE.rst
rafm-1.1.4.dist-info/WHEEL
rafm-1.1.4.dist-info/METADATA
rafm-1.1.4.dist-info/RECORD
