Metadata-Version: 2.1
Name: rafm
Version: 1.1.4
Summary: rafm
Home-page: https://github.com/joelb123/rafm
License: MIT
Keywords: science,biology,bioinformatics,pharmacology,data science,protein,sequences,structural biology,AlphaFold
Author: Joel Berendzen
Author-email: joel@generisbio.com
Requires-Python: >=3.8.1,<3.11
Classifier: Development Status :: 5 - Production/Stable
Classifier: Environment :: Console
Classifier: Intended Audience :: Science/Research
Classifier: License :: OSI Approved :: MIT License
Classifier: Operating System :: OS Independent
Classifier: Programming Language :: Python :: 3
Classifier: Programming Language :: Python :: 3.10
Classifier: Programming Language :: Python :: 3.8
Classifier: Programming Language :: Python :: 3.9
Classifier: Topic :: Scientific/Engineering :: Bio-Informatics
Requires-Dist: biopython
Requires-Dist: loguru
Requires-Dist: matplotlib
Requires-Dist: numpy
Requires-Dist: pandas
Requires-Dist: scipy
Requires-Dist: seaborn
Requires-Dist: statsdict
Requires-Dist: stmol
Requires-Dist: streamlit
Requires-Dist: typer
Project-URL: Changelog, https://github.com/joelb123/rafm/releases
Project-URL: Documentation, https://rafm.readthedocs.io
Project-URL: Repository, https://github.com/joelb123/rafm
